{"inkVersion":20,"root":[["\n",{"->":"main"},["done",{"#f":5,"#n":"g-0"}],null],"done",{"main":["ev","str","^PuebloCinematica","/str","/ev",{"VAR=":"destino","re":true},{"#":"speaker: Jeringuito"},{"#":"portrait: 0"},"^Ay, que ya no sale humo.","\n","^Me casaría contigo ahora mismo.","\n",{"#":"speaker: Tanic"},{"#":"portrait: 1"},"^Jaja, no puede ser, ya soy ancla de otra sierra, pero me alegra haberte ayudado. ¿A dónde pensabas ir?","\n",{"#":"speaker: Jeringuito"},{"#":"portrait: 0"},"^Tengo que ir a Cayeferro. Soy médico y planeaba ayudar por allí con esa epidemia que parecen tener.","\n",{"#":"speaker: Tanic"},{"#":"portrait: 1"},"^¿A Cayeferro? ¿¡No me digas!? Llevo tiempo intentando encontrar la manera de ir, pero sin barco con el que navegar la llevaba clara…","\n",{"#":"speaker: Jeringuito"},{"#":"portrait: 0"},"^¿Te parece que hagamos un trato?","\n",{"#":"speaker: Tanic"},{"#":"portrait: 1"},"^¿Qué clase de trato?","\n",{"#":"speaker: Jeringuito"},{"#":"portrait: 0"},"^Ya que también tienes que ir a Cayeferro y está claro que no tengo idea de manejar un barco,","\n","^¿qué tal si vamos los dos y así me aseguro de no morir en el intento?","\n",{"#":"speaker: Tanic"},{"#":"portrait: 1"},"^¡Me parece estupendo!","\n",{"#":"speaker: Jeringuito"},{"#":"portrait: 0"},"^Entonces, ¡partamos de inmediato!","\n","end",{"#f":1}],"global decl":["ev","str","^ninguno","/str",{"VAR=":"minijuego"},"str","^","/str",{"VAR=":"destino"},"str","^","/str",{"VAR=":"eleccion"},"str","^true","/str",{"VAR=":"partir"},"str","^true","/str",{"VAR=":"paraselva"},"str","^","/str",{"VAR=":"clinicaDonado"},"/ev","end",null],"#f":1}],"listDefs":{}}